pysimplevtk/__init__.py
pysimplevtk/paraview_data.py
pysimplevtk/polydata.py
pysimplevtk/rectilinear_grid.py
pysimplevtk/utilities/__init__.py
pysimplevtk/utilities/global_point_list.py
pysimplevtk-0.3.0.dist-info/DESCRIPTION.rst
pysimplevtk-0.3.0.dist-info/METADATA
pysimplevtk-0.3.0.dist-info/RECORD
pysimplevtk-0.3.0.dist-info/WHEEL
pysimplevtk-0.3.0.dist-info/metadata.json
pysimplevtk-0.3.0.dist-info/top_level.txt
