Metadata-Version: 2.0
Name: pysimplevtk
Version: 0.3.0
Summary: High level wrapper to work with vtk xml files.
Home-page: https://github.com/ZeeD26/pysimplevtk
Author: Dominik Steinberger
Author-email: zeed.dev@icloud.com
License: BSD
Platform: UNKNOWN
Requires-Dist: numpy
